rife_ncnn_vulkan_python/__init__.py
rife_ncnn_vulkan_python/_rife_ncnn_vulkan_wrapper.so
rife_ncnn_vulkan_python/rife_ncnn_vulkan.py
rife_ncnn_vulkan_python/rife_ncnn_vulkan_wrapper.py
rife_ncnn_vulkan_python/vcomp140.dll
rife_ncnn_vulkan_python/include/glslang/build_info.h
rife_ncnn_vulkan_python/include/glslang/Include/BaseTypes.h
rife_ncnn_vulkan_python/include/glslang/Include/Common.h
rife_ncnn_vulkan_python/include/glslang/Include/ConstantUnion.h
rife_ncnn_vulkan_python/include/glslang/Include/InfoSink.h
rife_ncnn_vulkan_python/include/glslang/Include/InitializeGlobals.h
rife_ncnn_vulkan_python/include/glslang/Include/PoolAlloc.h
rife_ncnn_vulkan_python/include/glslang/Include/ResourceLimits.h
rife_ncnn_vulkan_python/include/glslang/Include/ShHandle.h
rife_ncnn_vulkan_python/include/glslang/Include/SpirvIntrinsics.h
rife_ncnn_vulkan_python/include/glslang/Include/Types.h
rife_ncnn_vulkan_python/include/glslang/Include/arrays.h
rife_ncnn_vulkan_python/include/glslang/Include/glslang_c_interface.h
rife_ncnn_vulkan_python/include/glslang/Include/glslang_c_shader_types.h
rife_ncnn_vulkan_python/include/glslang/Include/intermediate.h
rife_ncnn_vulkan_python/include/glslang/MachineIndependent/Initialize.h
rife_ncnn_vulkan_python/include/glslang/MachineIndependent/LiveTraverser.h
rife_ncnn_vulkan_python/include/glslang/MachineIndependent/ParseHelper.h
rife_ncnn_vulkan_python/include/glslang/MachineIndependent/RemoveTree.h
rife_ncnn_vulkan_python/include/glslang/MachineIndependent/Scan.h
rife_ncnn_vulkan_python/include/glslang/MachineIndependent/ScanContext.h
rife_ncnn_vulkan_python/include/glslang/MachineIndependent/SymbolTable.h
rife_ncnn_vulkan_python/include/glslang/MachineIndependent/Versions.h
rife_ncnn_vulkan_python/include/glslang/MachineIndependent/attribute.h
rife_ncnn_vulkan_python/include/glslang/MachineIndependent/gl_types.h
rife_ncnn_vulkan_python/include/glslang/MachineIndependent/glslang_tab.cpp.h
rife_ncnn_vulkan_python_tntwise-1.4.5.dist-info/licenses/LICENSE
rife_ncnn_vulkan_python_tntwise-1.4.5.dist-info/METADATA
rife_ncnn_vulkan_python_tntwise-1.4.5.dist-info/WHEEL
rife_ncnn_vulkan_python_tntwise-1.4.5.dist-info/top_level.txt
rife_ncnn_vulkan_python_tntwise-1.4.5.dist-info/RECORD
