Metadata-Version: 2.4
Name: rife-ncnn-vulkan-python-tntwise
Version: 1.4.5
Summary: A Python FFI of nihui/rife-ncnn-vulkan achieved with SWIG
Home-page: https://github.com/TNTwise/rife-ncnn-vulkan-python/
Author: ArchieMeng
Author-email: archiemeng@protonmail.com
Maintainer: K4YT3X, TNTwise
Maintainer-email: i@k4yt3x.com
License: MIT
Keywords: rife,ncnn,vulkan,swig
Classifier: Environment :: Console
Classifier: Programming Language :: Python
Classifier: Programming Language :: Python :: 3
Classifier: Operating System :: OS Independent
Requires-Python: >=3.6
License-File: LICENSE
Requires-Dist: pillow
Dynamic: license-file
